frm/__init__.py
frm/enums/__init__.py
frm/enums/helper.py
frm/enums/term_structures.py
frm/enums/utils.py
frm/instruments/FRA.png
frm/instruments/__init__.py
frm/instruments/leg.py
frm/instruments/swap.py
frm/pricing_engine/__init__.py
frm/pricing_engine/black76_bachelier.py
frm/pricing_engine/clewlow_strickland_1_factor.py
frm/pricing_engine/cosine_method_generic.py
frm/pricing_engine/garman_kohlhagen.py
frm/pricing_engine/geometric_brownian_motion.py
frm/pricing_engine/heston.py
frm/pricing_engine/hw1f.py
frm/pricing_engine/monte_carlo_generic.py
frm/pricing_engine/option.py
frm/pricing_engine/sabr.py
frm/pricing_engine/volatility_generic.py
frm/pricing_engine/in_progress/gbm_speed_exploration.py
frm/pricing_engine/in_progress/monte_carlo_multiprocessing.py
frm/term_structures/__init__.py
frm/term_structures/bootstrap_helpers.py
frm/term_structures/fx_helpers.py
frm/term_structures/fx_volatility_surface.py
frm/term_structures/historical_swap_index_fixings.py
frm/term_structures/iban_ccys.py
frm/term_structures/interest_rate_option_helpers.py
frm/term_structures/optionlet.py
frm/term_structures/swap_curve.py
frm/term_structures/swaption.py
frm/term_structures/zero_curve.py
frm/term_structures/zero_curve_helpers.py
frm/term_structures/archive/fx_volatility_surface_old.py
frm/term_structures/archive/historical_swap_index_fixings_old.py
frm/term_structures/archive/ois_fixings.py
frm/term_structures/archive/swap_curve_old.py
frm/utils/CCY_HOLIDAY.pkl
frm/utils/LOCALE_HOLIDAY.pkl
frm/utils/__init__.py
frm/utils/business_day_calendar.py
frm/utils/calendar_map.xlsx
frm/utils/currency_holidays.xlsx
frm/utils/custom_errors_and_warnings.py
frm/utils/daycount.py
frm/utils/interpolation.py
frm/utils/schedule.py
frm/utils/schedule_old.py
frm/utils/settings.py
frm/utils/tenor.py
frm/utils/utilities.py
frm-0.0.35.dist-info/METADATA
frm-0.0.35.dist-info/WHEEL
frm-0.0.35.dist-info/licenses/LICENSE
frm-0.0.35.dist-info/RECORD
