Metadata-Version: 2.4
Name: frm
Version: 0.0.35
Summary: A python package for quantitative finance and derivative pricing
Project-URL: Homepage, https://github.com/shasafoster/frm
Project-URL: Website, https://frmcalcs.com/
Author-email: Shasa Foster <shasa.foster@frmcalcs.com>
License-File: LICENSE
Classifier: License :: OSI Approved :: Mozilla Public License 2.0 (MPL 2.0)
Classifier: Operating System :: OS Independent
Classifier: Programming Language :: Python :: 3
Requires-Python: <3.12,>=3.11
Requires-Dist: dill
Requires-Dist: holidays
Requires-Dist: matplotlib
Requires-Dist: numba>=0.60.0
Requires-Dist: numpy
Requires-Dist: openpyxl
Requires-Dist: pandas
Requires-Dist: prettytable
Requires-Dist: pycountry
Requires-Dist: pytest
Requires-Dist: scipy
Requires-Dist: snakeviz
